[
    {
        "ID": 27,
        "Value": "AECA",
        "isActive": true,
        "DisplayOrder": 0,
        "UsedInOFACSanctions": false,
        "UsedInOFACFAQs": false,
        "UsedInOFACGuidance": false,
        "UsedInSecondarySanctions": false,
        "UsedInBISSanctions": true,
        "UsedInBISFAQs": false,
        "UsedInBISGuidance": false,
        "UsedInDDTCSanctions": false,
        "UsedInDDTCFAQs": false,
        "UsedInDDTCGuidance": false,
        "LookupTable": 7
    },
    {
        "ID": 26,
        "Value": "EAA",
        "isActive": true,
        "DisplayOrder": 0,
        "UsedInOFACSanctions": false,
        "UsedInOFACFAQs": false,
        "UsedInOFACGuidance": false,
        "UsedInSecondarySanctions": false,
        "UsedInBISSanctions": true,
        "UsedInBISFAQs": false,
        "UsedInBISGuidance": false,
        "UsedInDDTCSanctions": false,
        "UsedInDDTCFAQs": false,
        "UsedInDDTCGuidance": false,
        "LookupTable": 7
    },
    {
        "ID": 28,
        "Value": "ECRA",
        "isActive": true,
        "DisplayOrder": 0,
        "UsedInOFACSanctions": false,
        "UsedInOFACFAQs": false,
        "UsedInOFACGuidance": false,
        "UsedInSecondarySanctions": false,
        "UsedInBISSanctions": true,
        "UsedInBISFAQs": false,
        "UsedInBISGuidance": false,
        "UsedInDDTCSanctions": false,
        "UsedInDDTCFAQs": false,
        "UsedInDDTCGuidance": false,
        "LookupTable": 7
    },
    {
        "ID": 30,
        "Value": "FNKDA",
        "isActive": true,
        "DisplayOrder": 0,
        "UsedInOFACSanctions": true,
        "UsedInOFACFAQs": false,
        "UsedInOFACGuidance": false,
        "UsedInSecondarySanctions": false,
        "UsedInBISSanctions": false,
        "UsedInBISFAQs": false,
        "UsedInBISGuidance": false,
        "UsedInDDTCSanctions": false,
        "UsedInDDTCFAQs": false,
        "UsedInDDTCGuidance": false,
        "LookupTable": 7
    },
    {
        "ID": 16,
        "Value": "IEEPA",
        "isActive": true,
        "DisplayOrder": 0,
        "UsedInOFACSanctions": true,
        "UsedInOFACFAQs": false,
        "UsedInOFACGuidance": false,
        "UsedInSecondarySanctions": false,
        "UsedInBISSanctions": true,
        "UsedInBISFAQs": false,
        "UsedInBISGuidance": false,
        "UsedInDDTCSanctions": false,
        "UsedInDDTCFAQs": false,
        "UsedInDDTCGuidance": false,
        "LookupTable": 7
    },
    {
        "ID": 29,
        "Value": "The Espionage Act",
        "isActive": true,
        "DisplayOrder": 0,
        "UsedInOFACSanctions": false,
        "UsedInOFACFAQs": false,
        "UsedInOFACGuidance": false,
        "UsedInSecondarySanctions": false,
        "UsedInBISSanctions": true,
        "UsedInBISFAQs": false,
        "UsedInBISGuidance": false,
        "UsedInDDTCSanctions": false,
        "UsedInDDTCFAQs": false,
        "UsedInDDTCGuidance": false,
        "LookupTable": 7
    },
    {
        "ID": 31,
        "Value": "TWEA",
        "isActive": true,
        "DisplayOrder": 0,
        "UsedInOFACSanctions": true,
        "UsedInOFACFAQs": false,
        "UsedInOFACGuidance": false,
        "UsedInSecondarySanctions": false,
        "UsedInBISSanctions": false,
        "UsedInBISFAQs": false,
        "UsedInBISGuidance": false,
        "UsedInDDTCSanctions": false,
        "UsedInDDTCFAQs": false,
        "UsedInDDTCGuidance": false,
        "LookupTable": 7
    }
]