[
  {
    "ProgramID": "BY",
    "Program": "Belarus",
    "AuthorityCount": 17,
    "ActiveAuthorityCount": 17,
    "ProgramType": "country"
  },
  {
    "ProgramID": "BA",
    "Program": "Bosnia And Herzegovina",
    "AuthorityCount": 12,
    "ActiveAuthorityCount": 12,
    "ProgramType": "country"
  },
  {
    "ProgramID": "BI",
    "Program": "Burundi",
    "AuthorityCount": 13,
    "ActiveAuthorityCount": 0,
    "ProgramType": "country"
  },
  {
    "ProgramID": "CF",
    "Program": "Central African Republic",
    "AuthorityCount": 14,
    "ActiveAuthorityCount": 14,
    "ProgramType": "country"
  },
  {
    "ProgramID": "CN",
    "Program": "China",
    "AuthorityCount": 4,
    "ActiveAuthorityCount": 4,
    "ProgramType": "country"
  },
  {
    "ProgramID": "HR",
    "Program": "Croatia",
    "AuthorityCount": 12,
    "ActiveAuthorityCount": 12,
    "ProgramType": "country"
  },
  {
    "ProgramID": "CU",
    "Program": "Cuba",
    "AuthorityCount": 4,
    "ActiveAuthorityCount": 4,
    "ProgramType": "country"
  },
  {
    "ProgramID": "CD",
    "Program": "Democratic Republic of the Congo",
    "AuthorityCount": 15,
    "ActiveAuthorityCount": 15,
    "ProgramType": "country"
  },
  {
    "ProgramID": "ET",
    "Program": "Ethiopia",
    "AuthorityCount": 16,
    "ActiveAuthorityCount": 16,
    "ProgramType": "country"
  },
  {
    "ProgramID": "IR",
    "Program": "Iran",
    "AuthorityCount": 144,
    "ActiveAuthorityCount": 144,
    "ProgramType": "country"
  },
  {
    "ProgramID": "IQ",
    "Program": "Iraq",
    "AuthorityCount": 6,
    "ActiveAuthorityCount": 6,
    "ProgramType": "country"
  },
  {
    "ProgramID": "KV",
    "Program": "Kosovo",
    "AuthorityCount": 12,
    "ActiveAuthorityCount": 12,
    "ProgramType": "country"
  },
  {
    "ProgramID": "LB",
    "Program": "Lebanon",
    "AuthorityCount": 4,
    "ActiveAuthorityCount": 4,
    "ProgramType": "country"
  },
  {
    "ProgramID": "LY",
    "Program": "Libya",
    "AuthorityCount": 17,
    "ActiveAuthorityCount": 17,
    "ProgramType": "country"
  },
  {
    "ProgramID": "ML",
    "Program": "Mali",
    "AuthorityCount": 12,
    "ActiveAuthorityCount": 12,
    "ProgramType": "country"
  },
  {
    "ProgramID": "MD",
    "Program": "Moldova",
    "AuthorityCount": 4,
    "ActiveAuthorityCount": 4,
    "ProgramType": "country"
  },
  {
    "ProgramID": "ME",
    "Program": "Montenegro",
    "AuthorityCount": 12,
    "ActiveAuthorityCount": 12,
    "ProgramType": "country"
  },
  {
    "ProgramID": "MM",
    "Program": "Myanmar",
    "AuthorityCount": 13,
    "ActiveAuthorityCount": 13,
    "ProgramType": "country"
  },
  {
    "ProgramID": "NI",
    "Program": "Nicaragua",
    "AuthorityCount": 13,
    "ActiveAuthorityCount": 13,
    "ProgramType": "country"
  },
  {
    "ProgramID": "KP",
    "Program": "North Korea",
    "AuthorityCount": 81,
    "ActiveAuthorityCount": 81,
    "ProgramType": "country"
  },
  {
    "ProgramID": "RU",
    "Program": "Russia",
    "AuthorityCount": 80,
    "ActiveAuthorityCount": 80,
    "ProgramType": "country"
  },
  {
    "ProgramID": "RS",
    "Program": "Serbia",
    "AuthorityCount": 12,
    "ActiveAuthorityCount": 12,
    "ProgramType": "country"
  },
  {
    "ProgramID": "SO",
    "Program": "Somalia",
    "AuthorityCount": 10,
    "ActiveAuthorityCount": 10,
    "ProgramType": "country"
  },
  {
    "ProgramID": "SS",
    "Program": "South Sudan",
    "AuthorityCount": 13,
    "ActiveAuthorityCount": 13,
    "ProgramType": "country"
  },
  {
    "ProgramID": "SD",
    "Program": "Sudan",
    "AuthorityCount": 12,
    "ActiveAuthorityCount": 12,
    "ProgramType": "country"
  },
  {
    "ProgramID": "SY",
    "Program": "Syria",
    "AuthorityCount": 48,
    "ActiveAuthorityCount": 48,
    "ProgramType": "country"
  },
  {
    "ProgramID": "UA",
    "Program": "Ukraine",
    "AuthorityCount": 55,
    "ActiveAuthorityCount": 55,
    "ProgramType": "country"
  },
  {
    "ProgramID": "VE",
    "Program": "Venezuela",
    "AuthorityCount": 18,
    "ActiveAuthorityCount": 18,
    "ProgramType": "country"
  },
  {
    "ProgramID": "YE",
    "Program": "Yemen",
    "AuthorityCount": 4,
    "ActiveAuthorityCount": 4,
    "ProgramType": "country"
  },
  {
    "ProgramID": "ZW",
    "Program": "Zimbabwe",
    "AuthorityCount": 12,
    "ActiveAuthorityCount": 12,
    "ProgramType": "country"
  },
  {
    "ProgramID": "19",
    "Program": "Chemical & Biological Weapons",
    "AuthorityCount": 1,
    "ActiveAuthorityCount": 1,
    "ProgramType": "program"
  },
  {
    "ProgramID": "21",
    "Program": "Counter-Narcotics",
    "AuthorityCount": 3,
    "ActiveAuthorityCount": 3,
    "ProgramType": "program"
  },
  {
    "ProgramID": "22",
    "Program": "Counter-Terrorism",
    "AuthorityCount": 4,
    "ActiveAuthorityCount": 4,
    "ProgramType": "program"
  },
  {
    "ProgramID": "24",
    "Program": "Cyber",
    "AuthorityCount": 1,
    "ActiveAuthorityCount": 1,
    "ProgramType": "program"
  },
  {
    "ProgramID": "26",
    "Program": "Election Interference",
    "AuthorityCount": 1,
    "ActiveAuthorityCount": 1,
    "ProgramType": "program"
  },
  {
    "ProgramID": "27",
    "Program": "Global Magnitsky",
    "AuthorityCount": 2,
    "ActiveAuthorityCount": 2,
    "ProgramType": "program"
  },
  {
    "ProgramID": "29",
    "Program": "Non-Proliferation",
    "AuthorityCount": 3,
    "ActiveAuthorityCount": 3,
    "ProgramType": "program"
  },
  {
    "ProgramID": "42",
    "Program": "Transnational Criminal Organizations (TCO)",
    "AuthorityCount": 1,
    "ActiveAuthorityCount": 1,
    "ProgramType": "program"
  }
]